easygame/__init__.py
easygame-1.3.0.dist-info/LICENSE
easygame-1.3.0.dist-info/METADATA
easygame-1.3.0.dist-info/WHEEL
easygame-1.3.0.dist-info/top_level.txt
easygame-1.3.0.dist-info/RECORD
