Metadata-Version: 2.1
Name: easygame
Version: 1.3.0
Summary: 一个写游戏的框架,封装pygame
Home-page: UNKNOWN
Author: stripe-python
Author-email: 13513519246@139.com
Maintainer: stripe-python
Maintainer-email: 13513519246@139.com
License: UNKNOWN
Platform: UNKNOWN
Classifier: Programming Language :: Python :: 3
Classifier: License :: OSI Approved :: MIT License
Classifier: Operating System :: OS Independent
Requires-Python: >=3.6
Requires-Dist: pygame
Requires-Dist: pyperclip
Requires-Dist: playsound
Requires-Dist: pycaw
Requires-Dist: opencv-python
Requires-Dist: jinja2
Requires-Dist: webbrowser
